jinja2_render.py
jinja2_render-1.3.dist-info/LICENSE
jinja2_render-1.3.dist-info/METADATA
jinja2_render-1.3.dist-info/WHEEL
jinja2_render-1.3.dist-info/entry_points.txt
jinja2_render-1.3.dist-info/top_level.txt
jinja2_render-1.3.dist-info/zip-safe
jinja2_render-1.3.dist-info/RECORD
