Metadata-Version: 2.1
Name: jinja2-render
Version: 1.3
Summary: jinja2-render – A CLI tool to render Jinja2 templates
Home-page: https://github.com/pklaus/jinja2-render
Author: Philipp Klaus
Author-email: philipp.l.klaus@web.de
License: GPL
Keywords: Context-dependent Jinja2 Template Rendering CLI Docker Dockerfile
Platform: any
Classifier: Development Status :: 4 - Beta
Classifier: Operating System :: OS Independent
Classifier: License :: OSI Approved :: MIT License
Classifier: Programming Language :: Python
Classifier: Programming Language :: Python :: 3
Classifier: Topic :: System :: Archiving :: Packaging
Requires-Dist: jinja2
